gurux_common/GXCommon.py
gurux_common/IGXMedia.py
gurux_common/IGXMediaListener.py
gurux_common/MediaStateEventArgs.py
gurux_common/PropertyChangedEventArgs.py
gurux_common/ReceiveEventArgs.py
gurux_common/ReceiveParameters.py
gurux_common/TimeoutException.py
gurux_common/TraceEventArgs.py
gurux_common/__init__.py
gurux_common/enums/MediaState.py
gurux_common/enums/TraceLevel.py
gurux_common/enums/TraceTypes.py
gurux_common/enums/__init__.py
gurux_common/io/BaudRate.py
gurux_common/io/Handshake.py
gurux_common/io/Parity.py
gurux_common/io/StopBits.py
gurux_common/io/__init__.py
gurux_common-1.0.13.dist-info/LICENSE
gurux_common-1.0.13.dist-info/METADATA
gurux_common-1.0.13.dist-info/WHEEL
gurux_common-1.0.13.dist-info/top_level.txt
gurux_common-1.0.13.dist-info/RECORD
