Metadata-Version: 2.1
Name: gurux-common
Version: 1.0.13
Summary: Gurux common helpers for device commmunication.
Home-page: https://github.com/gurux/gurux.common.python
Author: Gurux Ltd
Author-email: gurux@gurux.org
License: UNKNOWN
Platform: UNKNOWN
Classifier: Programming Language :: Python :: 2.7
Classifier: Programming Language :: Python :: 3
Classifier: Programming Language :: Python :: 3.3
Classifier: Programming Language :: Python :: 3.4
Classifier: Programming Language :: Python :: 3.5
Classifier: Programming Language :: Python :: 3.6
Classifier: Programming Language :: Python :: 3.7
Classifier: License :: OSI Approved :: GNU General Public License v2 (GPLv2)
Classifier: Operating System :: OS Independent
